llama_index/llms/mistralai/__init__.py
llama_index/llms/mistralai/base.py
llama_index/llms/mistralai/utils.py
llama_index_llms_mistralai-0.8.2.dist-info/METADATA
llama_index_llms_mistralai-0.8.2.dist-info/WHEEL
llama_index_llms_mistralai-0.8.2.dist-info/licenses/LICENSE
llama_index_llms_mistralai-0.8.2.dist-info/RECORD
