Metadata-Version: 2.4
Name: llama-index-llms-mistralai
Version: 0.8.2
Summary: llama-index llms mistral ai integration
Author-email: Your Name <you@example.com>
License-Expression: MIT
License-File: LICENSE
Requires-Python: <4.0,>=3.9
Requires-Dist: llama-index-core<0.15,>=0.14.3
Requires-Dist: mistralai>=1.8.2
